[
  {
    "Field": "log_id",
    "Type": "int",
    "Null": "NO",
    "Key": "PRI",
    "Default": null,
    "Extra": "auto_increment"
  },
  {
    "Field": "login",
    "Type": "varchar(100)",
    "Null": "NO",
    "Key": "",
    "Default": null,
    "Extra": ""
  },
  {
    "Field": "user_id",
    "Type": "int",
    "Null": "YES",
    "Key": "",
    "Default": null,
    "Extra": ""
  },
  {
    "Field": "ip_address",
    "Type": "varchar(45)",
    "Null": "YES",
    "Key": "",
    "Default": null,
    "Extra": ""
  },
  {
    "Field": "user_agent",
    "Type": "varchar(255)",
    "Null": "YES",
    "Key": "",
    "Default": null,
    "Extra": ""
  },
  {
    "Field": "success",
    "Type": "tinyint(1)",
    "Null": "NO",
    "Key": "",
    "Default": null,
    "Extra": ""
  },
  {
    "Field": "failure_reason",
    "Type": "varchar(100)",
    "Null": "YES",
    "Key": "",
    "Default": null,
    "Extra": ""
  },
  {
    "Field": "attempt_time",
    "Type": "datetime",
    "Null": "YES",
    "Key": "",
    "Default": "CURRENT_TIMESTAMP",
    "Extra": "DEFAULT_GENERATED"
  }
]